README.md
setup.py
STAVAG/STAVAG.py
STAVAG/__init__.py
STAVAG.egg-info/PKG-INFO
STAVAG.egg-info/SOURCES.txt
STAVAG.egg-info/dependency_links.txt
STAVAG.egg-info/not-zip-safe
STAVAG.egg-info/requires.txt
STAVAG.egg-info/top_level.txt