Metadata-Version: 2.1
Name: STAVAG
Version: 1.0.1
Summary: Uncovering directionally and temporally variable genes with STAVAG
Home-page: https://github.com/Zhanglabtools/STAVAG
Author: Qunlun Shen
Author-email: knotnet@foxmail.com
License: MIT
Requires-Dist: requests
